Workbook

Sheet Tableau de Bord
B2: 2A-COMMERCE QUINCAILLERIE - TABLEAU DE BORD
B3: Indicateurs clés de performance & suivi global du stock
B5: CHIFFRE D'AFFAIRES TOTAL | D5: MARGE BRUTE TOTALE | F5: VALEUR DU STOCK ACTUEL | H5: ARTICLES EN ALERTE
B6: =SUM(Mouvements!G5:G990) -> 2639800 | D6: {=SUMPRODUCT((Mouvements!B5:B990="Sortie")*(Mouvements!E5:E990)*(Mouvements!F5:F990-_xludf.XLOOKUP(Mouvements!C5:C990,Catalogue!A5:A1379,Catalogue!F5:F1375,0)))} -> #NAME? | F6: {=SUMPRODUCT(Catalogue!N5:N1375*Catalogue!F5:F1375)} -> 4145012 | H6: =COUNTIF(Catalogue!P5:P1375, "RÉAPPROVISIONNER") -> 350
B9: RÉCAPITULATIF PAR CATÉGORIE
B10: Catégorie | C10: Nb Articles | D10: Valeur Stock (Achat) | E10: Ventes Cumulées (FCFA)
B11: Gros œuvre | C11: =COUNTIF(Catalogue!C$5:C$231, B11) -> 10 | D11: {=SUMPRODUCT((Catalogue!C$5:C$231=B11)*(Catalogue!N$5:N$231)*(Catalogue!F$5:F$231))} -> 477654 | E11: =SUMIFS(Mouvements!G$5:G$990, Mouvements!D$5:D$990, B11, Mouvements!B$5:B$990, "Sortie") -> 0
B12: Ferraille | C12: =COUNTIF(Catalogue!C$5:C$231, B12) -> 11 | D12: {=SUMPRODUCT((Catalogue!C$5:C$231=B12)*(Catalogue!N$5:N$231)*(Catalogue!F$5:F$231))} -> 37250 | E12: =SUMIFS(Mouvements!G$5:G$990, Mouvements!D$5:D$990, B12, Mouvements!B$5:B$990, "Sortie") -> 0
B13: Plomberie | C13: =COUNTIF(Catalogue!C$5:C$231, B13) -> 78 | D13: {=SUMPRODUCT((Catalogue!C$5:C$231=B13)*(Catalogue!N$5:N$231)*(Catalogue!F$5:F$231))} -> 602050 | E13: =SUMIFS(Mouvements!G$5:G$990, Mouvements!D$5:D$990, B13, Mouvements!B$5:B$990, "Sortie") -> 0
B14: Électricité | C14: =COUNTIF(Catalogue!C$5:C$231, B14) -> 29 | D14: {=SUMPRODUCT((Catalogue!C$5:C$231=B14)*(Catalogue!N$5:N$231)*(Catalogue!F$5:F$231))} -> 804500 | E14: =SUMIFS(Mouvements!G$5:G$990, Mouvements!D$5:D$990, B14, Mouvements!B$5:B$990, "Sortie") -> 0
B15: Outillage / Peinture | C15: =COUNTIF(Catalogue!C$5:C$231, B15) -> 99 | D15: {=SUMPRODUCT((Catalogue!C$5:C$231=B15)*(Catalogue!N$5:N$231)*(Catalogue!F$5:F$231))} -> 902358 | E15: =SUMIFS(Mouvements!G$5:G$990, Mouvements!D$5:D$990, B15, Mouvements!B$5:B$990, "Sortie") -> 0
B16: TOTAL | C16: =SUM(C11:C15) -> 227 | D16: =SUM(D11:D15) -> 2823812 | E16: =SUM(E11:E15) -> 0

Sheet Catalogue
A2: CATALOGUE & ÉTAT DU STOCK
A3: Liste des articles, tarification et suivi automatisé des stocks
A4: Marque | B4: Désignation | C4: Catégorie | D4: Unité | E4: Prix au Mètre/Kg | F4: Prix Achat (FCFA) | G4: Prix Vente (FCFA) | H4: Marge (%) | I4: Stock Initial | J4: Seuil mini de vente | K4: Seuil mini de vente au metre/Kg | L4: Entrées | M4: Sorties | N4: Stock Actuel | O4: Seuil Alerte | P4: Statut Stock | Q4: Valeur Stock (FCFA)
A5: CIM IVOIRE | B5: Ciment CPJ 42.5 (Sachet 50kg) | C5: Gros œuvre | D5: Sac | F5: 4500 | G5: 5000 | H5: 0.11111111 | I5: 15 | J5: 5000 | L5: 0 | M5: 0 | N5: 15 | O5: 20 | P5: RÉAPPROVISIONNER | Q5: 67500
A6: SOTICI | B6: Fer à béton Ø 10 (Barre 12m) | C6: Ferraille | D6: Barre | F6: 0 | G6: 0 | I6: 0 | L6: 0 | M6: 0 | N6: 0 | O6: 50 | P6: RÉAPPROVISIONNER | Q6: 0
B7: TUYAUX PRESSION 16/20 6M PN 10 | C7: Plomberie | D7: Barre | E7: 600 | F7: 1500 | G7: 3000 | H7: 1 | I7: 40 | J7: 2500 | L7: 0 | M7: 0 | N7: 40 | O7: 10 | P7: OK | Q7: 60000
A8: DELUX INDUSTRAP | B8: Delux Peinture Vinilique Mat 30Kg EXT | C8: Outillage / Peinture | D8: Seau | F8: 23500 | G8: 25000 | H8: 0.063829787 | I8: 6 | J8: 24000 | L8: 0 | M8: 0 | N8: 6 | O8: 5 | P8: OK | Q8: 141000
A9: DELUX INDUSTRAP | B9: Delux Peinture Vinilique Mat 30Kg INT | C9: Outillage / Peinture | D9: Seau | F9: 21500 | G9: 23000 | H9: 0.069767442 | I9: 4 | J9: 22000 | L9: 0 | M9: 0 | N9: 4 | P9: OK | Q9: 86000
A10: PLASTICABLE | B10: Câble Électrique TH 2X1.5 (Rouleau 100m) | C10: Électricité | D10: Rouleau | E10: 600 | F10: 47500 | G10: 50000 | H10: 0.052631579 | I10: 1 | K10: 500 | L10: 0 | M10: 0 | N10: 1 | O10: 8 | P10: RÉAPPROVISIONNER | Q10: 47500
A11: B METERS | B11: SOUS COMPTEUR D'EAU EN FER GM | C11: Plomberie | D11: Unité | F11: 4000 | G11: 6000 | H11: 0.5 | I11: 1 | J11: 5000 | L11: 0 | M11: 0 | N11: 1 | P11: OK
A12: FORCE | B12: SOUS COMPTEUR D'EAU EN FER GM | C12: Plomberie | D12: Unité | F12: 4000 | G12: 6000 | H12: 0.5 | I12: 2 | J12: 5000 | L12: 0 | M12: 0 | N12: 2 | O12: 8 | P12: RÉAPPROVISIONNER | Q12: 8000
A13: INDUSTRAP | B13: Milano Peinture Vinilique 5Kg INT/EXT | C13: Outillage / Peinture | D13: Seau | F13: 2300 | G13: 3500 | H13: 0.52173913 | I13: 4 | J13: 3000 | L13: 0 | M13: 0 | N13: 4 | O13: 8 | P13: RÉAPPROVISIONNER | Q13: 9200
A14: INDUSTRAP | B14: Milano Peinture Vinilique 15Kg INT/EXT | C14: Outillage / Peinture | D14: Seau | F14: 7500 | G14: 8500 | H14: 0.13333333 | I14: 3 | J14: 8000 | L14: 0 | M14: 0 | N14: 3 | O14: 8 | P14: RÉAPPROVISIONNER | Q14: 22500
A15: INDUSTRAP | B15: Milano Peinture Vinilique 30Kg INT/EXT | C15: Outillage / Peinture | D15: Seau | F15: 14300 | G15: 16000 | H15: 0.11888112 | I15: 4 | J15: 15000 | L15: 0 | M15: 0 | N15: 4 | O15: 8 | P15: RÉAPPROVISIONNER | Q15: 57200
A16: INDUSTRAP | B16: TRAPEAU INT 5Kg | C16: Outillage / Peinture | D16: Seau | F16: 2200 | G16: 3000 | H16: 0.36363636 | I16: 6 | J16: 2700 | L16: 0 | M16: 0 | N16: 6 | O16: 8 | P16: RÉAPPROVISIONNER | Q16: 13200
A17: INDUSTRAP | B17: TRAPEAU INT 15Kg | C17: Outillage / Peinture | D17: Seau | F17: 6500 | G17: 8000 | H17: 0.23076923 | I17: 4 | J17: 8000 | L17: 0 | M17: 0 | N17: 4 | O17: 8 | P17: RÉAPPROVISIONNER | Q17: 26000
A18: INDUSTRAP | B18: TRAPEAU INT 30Kg | C18: Outillage / Peinture | D18: Seau | F18: 12500 | G18: 14000 | H18: 0.12 | I18: 3 | J18: 13500 | L18: 0 | M18: 0 | N18: 3 | O18: 8 | P18: RÉAPPROVISIONNER | Q18: 37500
A19: SNPC | B19: SUPER PLUS INT/EXT 5Kg | C19: Outillage / Peinture | D19: Seau | F19: 2300 | G19: 3500 | H19: 0.52173913 | J19: 3000 | L19: 0 | M19: 0 | N19: 0 | O19: 8 | P19: RÉAPPROVISIONNER | Q19: 0
A20: SNPC | B20: SUPER PLUS INT/EXT 15Kg | C20: Outillage / Peinture | D20: Seau | F20: 6300 | G20: 8000 | H20: 0.26984127 | L20: 0 | M20: 0 | N20: 0 | O20: 8 | P20: RÉAPPROVISIONNER | Q20: 0
A21: SIPPEC | B21: COUDE PVC 110 EVAC | C21: Plomberie | D21: Tuyaux | F21: 650 | G21: 1000 | H21: 0.53846154 | J21: 800 | L21: 0 | M21: 0 | N21: 0 | O21: 8 | P21: RÉAPPROVISIONNER | Q21: 0
A22: SETR | B22: BUTUME 20Kg | C22: Gros œuvre | D22: Sac | F22: 11500 | G22: 15000 | H22: 0.30434783 | I22: 2 | J22: 13000 | L22: 0 | M22: 0 | N22: 2 | O22: 8 | P22: RÉAPPROVISIONNER | Q22: 23000
A23: MEGALEC | B23: COFFRET 2 MODULES APPARENT 2702 | C23: Électricité | D23: Unité | F23: 300 | G23: 1000 | H23: 2.3333333 | I23: 5 | J23: 600 | L23: 0 | M23: 0 | N23: 5 | O23: 8 | P23: RÉAPPROVISIONNER | Q23: 1500
A24: FORCE | B24: Flexible de Mitigeur 60CM WK-JN04 | C24: Plomberie | D24: Unité | F24: 700 | G24: 1000 | H24: 0.42857143 | I24: 10 | J24: 1000 | L24: 0 | M24: 0 | N24: 10 | O24: 8 | P24: OK | Q24: 7000
A25: CHEVAL | B25: Colorant Jaune Oxyde | C25: Outillage / Peinture | D25: Unité | F25: 750 | G25: 1000 | H25: 0.33333333 | I25: 20 | J25: 1000 | L25: 0 | M25: 0 | N25: 19 | O25: 8 | P25: OK | Q25: 15000
A26: CHEVAL | B26: Colorant Jaune Vert | C26: Outillage / Peinture | D26: Unité | F26: 750 | G26: 1000 | H26: 0.33333333 | I26: 9 | L26: 0 | M26: 0 | N26: 8 | O26: 8 | P26: RÉAPPROVISIONNER | Q26: 6750
A27: CHEVAL | B27: Colorant Jaune Violet | C27: Outillage / Peinture | D27: Unité | F27: 750 | G27: 1000 | H27: 0.33333333 | L27: 0 | M27: 0 | N27: 0 | O27: 8 | P27: RÉAPPROVISIONNER | Q27: 0
A28: CHEVAL | B28: Colorant Jaune Orange | C28: Outillage / Peinture | D28: Unité | F28: 750 | G28: 1000 | H28: 0.33333333 | L28: 0 | M28: 0 | N28: 0 | O28: 8 | P28: RÉAPPROVISIONNER | Q28: 0
A29: CHEVAL | B29: Colorant Jaune Orange | C29: Outillage / Peinture | D29: Unité | F29: 750 | G29: 1000 | H29: 0.33333333 | L29: 0 | M29: 0 | N29: 0 | O29: 8 | P29: RÉAPPROVISIONNER | Q29: 0
A30: CHEVAL | B30: Colorant Jaune Rouge | C30: Outillage / Peinture | D30: Unité | F30: 750 | G30: 1000 | H30: 0.33333333 | L30: 0 | M30: 0 | N30: 0 | O30: 8 | P30: RÉAPPROVISIONNER | Q30: 0
A31: INDUSTRAP | B31: Colorant noir | C31: Outillage / Peinture | D31: Unité | F31: 750 | G31: 1000 | H31: 0.33333333 | L31: 0 | M31: 0 | N31: 0 | O31: 8 | P31: RÉAPPROVISIONNER | Q31: 0
A32: EMTOP | B32: Maillet en caoutchouc blanc 8OZ/220G/marteau pour carreaux | C32: Gros œuvre | D32: Unité | F32: 1600 | G32: 2500 | H32: 0.5625 | I32: 3 | J32: 2000 | L32: 0 | M32: 0 | N32: 3 | O32: 8 | P32: RÉAPPROVISIONNER | Q32: 4800
A33: HERO | B33: Baguette Chinoise 2.5/CT | C33: Gros œuvre | D33: Unité | F33: 1688 | G33: 2500 | H33: 0.48104265 | I33: 8 | J33: 2200 | L33: 0 | M33: 0 | N33: 8 | O33: 8 | P33: RÉAPPROVISIONNER | Q33: 13504
A34: HERO | B34: Baguette Chinoise 3.15/CT | C34: Gros œuvre | D34: Unité | F34: 3750 | G34: 5000 | H34: 0.33333333 | J34: 4500 | L34: 0 | M34: 0 | N34: 0 | O34: 8 | P34: RÉAPPROVISIONNER | Q34: 0
A35: FORCE | B35: ROBINET PUISAGE A BOISSEAU 16/20 | C35: Plomberie | D35: Unité | F35: 1750 | G35: 2500 | H35: 0.42857143 | J35: 2000 | L35: 0 | M35: 0 | N35: 0 | O35: 8 | P35: RÉAPPROVISIONNER | Q35: 0
A36: MAROC | B36: Gamette | C36: Gros œuvre | D36: Unité | F36: 1800 | G36: 3000 | H36: 0.66666667 | I36: 15 | J36: 2500 | L36: 0 | M36: 0 | N36: 15 | O36: 8 | P36: OK | Q36: 27000
A37: INDUSTRAP | B37: PORTE PAPIER PLASTIQUE | C37: Plomberie | D37: Unité | F37: 1000 | G37: 2500 | H37: 1.5 | I37: 20 | J37: 2000 | L37: 0 | M37: 0 | N37: 20 | O37: 8 | P37: OK | Q37: 20000
A38: INDUSTRAP | B38: PORTE SAVON PLASTIQUE | C38: Plomberie | D38: Unité | F38: 600 | G38: 2000 | H38: 2.3333333 | I38: 20 | J38: 1500 | L38: 0 | M38: 0 | N38: 20 | O38: 8 | P38: OK | Q38: 12000
A39: INDUSTRAP | B39: TABLETTE EN PLASTIQUE | C39: Plomberie | D39: Unité | F39: 1200 | G39: 3000 | H39: 1.5 | I39: 10 | J39: 2000 | L39: 0 | M39: 0 | N39: 10 | O39: 8 | P39: OK | Q39: 12000
A40: INDUSTRAP | B40: PORTE SERVIETTE EN PLASTIQUE | C40: Plomberie | D40: Unité | F40: 1000 | G40: 3000 | H40: 2 | I40: 10 | J40: 2000 | L40: 0 | M40: 0 | N40: 10 | O40: 8 | P40: OK | Q40: 10000
A41: FORCE | B41: PORTE SERVIETTECHROME 2 BRANCHES | C41: Plomberie | D41: Unité | F41: 2000 | G41: 5000 | H41: 1.5 | I41: 5 | J41: 3500 | L41: 0 | M41: 0 | N41: 5 | O41: 8 | P41: RÉAPPROVISIONNER | Q41: 10000
A42: FORCE | B42: TABLETTE EN ACIER 40CM | C42: Plomberie | D42: Unité | F42: 2500 | G42: 5000 | H42: 1 | I42: 6 | J42: 4000 | L42: 0 | M42: 0 | N42: 6 | O42: 8 | P42: RÉAPPROVISIONNER | Q42: 15000
A43: FORCE | B43: ENSEMNLE DE DOUCHE TRANSPARENT 6800 | C43: Plomberie | D43: ENSEMBLE | F43: 6000 | G43: 15000 | H43: 1.5 | I43: 1 | J43: 12000 | L43: 0 | M43: 0 | N43: 1 | O43: 8 | P43: RÉAPPROVISIONNER | Q43: 6000
A44: INDUSTRAP | B44: ABATTANT DE WC LOURD 2003/J850B | C44: Plomberie | D44: Unité | F44: 1750 | G44: 5000 | H44: 1.8571429 | I44: 10 | J44: 3500 | L44: 0 | M44: 0 | N44: 10 | O44: 8 | P44: OK | Q44: 17500
A45: FORCE | B45: ROULEAU A PEINDRE N°4 | C45: Outillage / Peinture | D45: Unité | F45: 275 | G45: 500 | H45: 0.81818182 | I45: 110 | J45: 500 | L45: 0 | M45: 0 | N45: 110 | O45: 8 | P45: OK | Q45: 30250
A46: FORCE | B46: ROULEAU A PEINDRE N°8 | C46: Outillage / Peinture | D46: Unité | F46: 575 | G46: 1000 | H46: 0.73913043 | I46: 40 | J46: 1000 | L46: 0 | M46: 0 | N46: 40 | O46: 8 | P46: OK | Q46: 23000
A47: FORCE | B47: ROULEAUX A PEINDRE N°1O | C47: Outillage / Peinture | D47: Unité | F47: 700 | G47: 1000 | H47: 0.42857143 | I47: 40 | J47: 1000 | L47: 0 | M47: 0 | N47: 40 | O47: 8 | P47: OK | Q47: 28000
... A52: France MODELE | B52: PINCEAU N°30 | C52: Outillage / Peinture | D52: Unité | F52: 150 | G52: 300 | H52: 1 | I52: 10 | J52: 250 | L52: 0 | M52: 0 | N52: 10 | O52: 8 | P52: OK | Q52: 1500
A53: France MODELE | B53: PINCEAU N°70 | C53: Outillage / Peinture | D53: Unité | F53: 350 | G53: 500 | H53: 0.42857143 | J53: 500 | L53: 0 | M53: 3 | N53: 7 | P53: OK | Q53: 0
A54: FORCE | B54: CHEVILLE + VIS N°10 50PCS/BTE | C54: Plomberie | D54: Unité | F54: 1000 | G54: 2000 | H54: 1 | I54: 10 | J54: 1500 | L54: 0 | M54: 0 | N54: 10 | O54: 8 | P54: OK | Q54: 10000
A55: FORCE | B55: CHEVILLE + VIS N°12 25PCS/BTE | C55: Plomberie | D55: Unité | F55: 700 | G55: 1000 | H55: 0.42857143 | I55: 10 | J55: 1000 | L55: 0 | M55: 3 | N55: 7 | O55: 8 | P55: RÉAPPROVISIONNER | Q55: 7000
A56: FORCE | B56: EVIER ORD DE CUISINE 1 TROU 1000X500X140 | C56: Plomberie | D56: Unité | F56: 4500 | G56: 8000 | H56: 0.77777778 | I56: 5 | J56: 7500 | L56: 0 | M56: 0 | N56: 5 | O56: 8 | P56: RÉAPPROVISIONNER | Q56: 22500
A57: FORCE | B57: GLOBE LED 24W | C57: Électricité | D57: Unité | F57: 2000 | G57: 4500 | H57: 1.25 | I57: 10 | J57: 3500 | L57: 0 | M57: 0 | N57: 10 | O57: 8 | P57: OK | Q57: 20000
A58: FORCE | B58: FLEXIBLE DE DOUCHE WK-SH04 | C58: Plomberie | D58: Unité | F58: 1200 | G58: 4500 | H58: 2.75 | I58: 9 | J58: 3000 | L58: 0 | M58: 0 | N58: 9 | O58: 8 | P58: OK | Q58: 10800
A59: PAINIE | B59: ROBINET DE CUISINE | C59: Plomberie | D59: Unité | F59: 3200 | G59: 8000 | H59: 1.5 | I59: 5 | J59: 6000 | L59: 0 | M59: 0 | N59: 5 | O59: 8 | P59: RÉAPPROVISIONNER | Q59: 16000
A60: PAINIE | B60: ROBINET DE LAVABO | C60: Plomberie | D60: Unité | F60: 3200 | G60: 8000 | H60: 1.5 | I60: 5 | J60: 6000 | L60: 0 | M60: 0 | N60: 5 | O60: 8 | P60: RÉAPPROVISIONNER | Q60: 16000
A61: PAINIE | B61: ROBINET DE DOUCHE | C61: Plomberie | D61: Unité | F61: 3200 | G61: 8000 | H61: 1.5 | I61: 5 | J61: 6000 | L61: 0 | M61: 0 | N61: 5 | O61: 8 | P61: RÉAPPROVISIONNER | Q61: 16000
A62: INDUSTRAP | B62: EMAIL Couleur Or | C62: Outillage / Peinture | D62: Boite | F62: 1300 | G62: 1500 | H62: 0.15384615 | I62: 2 | J62: 1500 | L62: 0 | M62: 0 | N62: 2 | O62: 8 | P62: RÉAPPROVISIONNER | Q62: 2600
A63: INDUSTRAP | B63: EMAIL autres couleurs | C63: Outillage / Peinture | D63: Boite | F63: 450 | G63: 500 | H63: 0.11111111 | I63: 25 | J63: 5000 | L63: 0 | M63: 0 | N63: 25 | O63: 8 | P63: OK | Q63: 11250
A64: INDUSTRAP | B64: ANTIROUILLE 1KG | C64: Outillage / Peinture | D64: Boite | F64: 1750 | G64: 2500 | H64: 0.42857143 | J64: 2500 | L64: 0 | M64: 0 | N64: 0 | O64: 8 | P64: RÉAPPROVISIONNER | Q64: 0
A65: AK PLAST CI | B65: SEAU NOIR | C65: Gros œuvre | D65: Seau | F65: 660 | G65: 1000 | H65: 0.51515152 | I65: 10 | J65: 1000 | L65: 0 | M65: 0 | N65: 10 | O65: 8 | P65: OK | Q65: 6600
A66: INDUSTRAP | B66: ORIGINAL PEINTURE A EAU 15KG | C66: Outillage / Peinture | D66: Seau | F66: 7500 | G66: 8000 | H66: 0.066666667 | I66: 1 | J66: 8000 | L66: 0 | M66: 0 | N66: 1 | O66: 8 | P66: RÉAPPROVISIONNER | Q66: 7500
A67: FORCE | B67: Colle Tangit Tube PM 50G-368 | C67: Plomberie | D67: Unité | F67: 500 | G67: 1000 | H67: 1 | I67: 3 | J67: 10000 | L67: 0 | M67: 0 | N67: 3 | O67: 8 | P67: RÉAPPROVISIONNER | Q67: 1500
A68: IFAN | B68: RACCORD UNION PVC 50 | C68: Plomberie | D68: Unité | F68: 500 | G68: 1000 | H68: 1 | I68: 5 | L68: 0 | M68: 0 | N68: 5 | O68: 8 | P68: RÉAPPROVISIONNER | Q68: 2500
A69: IFAN | B69: EMBOUT PVC D50 | C69: Plomberie | D69: Unité | F69: 1200 | G69: 2500 | H69: 1.0833333 | I69: 5 | J69: 2000 | L69: 0 | M69: 0 | N69: 5 | O69: 8 | P69: RÉAPPROVISIONNER | Q69: 6000
A70: INDUSTRAP | B70: Delux Peinture Glycero gris clair 4Kg | C70: Outillage / Peinture | D70: Boite | F70: 7500 | G70: 8000 | H70: 0.066666667 | J70: 8000 | L70: 0 | M70: 0 | N70: 0 | O70: 8 | P70: RÉAPPROVISIONNER | Q70: 0
A71: FADCO | B71: SOSA ROBINET LAVABO BEC LONG ROS4009 | C71: Plomberie | D71: Unité | F71: 7500 | G71: 15000 | H71: 1 | I71: 2 | J71: 12000 | L71: 0 | M71: 0 | N71: 2 | O71: 8 | P71: RÉAPPROVISIONNER | Q71: 15000
A72: FADCO | B72: SOSA ROBINET EVIER MURAL BEC "C" ROS4012 | C72: Plomberie | D72: Unité | F72: 6500 | G72: 15000 | H72: 1.3076923 | I72: 1 | J72: 12000 | L72: 0 | M72: 0 | N72: 1 | O72: 8 | P72: RÉAPPROVISIONNER | Q72: 6500
A73: FADCO | B73: ILDA MITIGEUR LAVABO 1101 | C73: Plomberie | D73: Unité | F73: 17500 | G73: 30000 | H73: 0.71428571 | I73: 1 | J73: 25000 | L73: 0 | M73: 0 | N73: 1 | O73: 8 | P73: RÉAPPROVISIONNER | Q73: 17500
A74: FADCO | B74: ILDA MITIGEUR DOUCHE 1104 | C74: Plomberie | D74: Unité | F74: 18000 | G74: 30000 | H74: 0.66666667 | I74: 1 | J74: 25000 | L74: 0 | M74: 0 | N74: 1 | O74: 8 | P74: RÉAPPROVISIONNER | Q74: 18000
A75: FADCO | B75: ILDA MITIGEUR CUISINE 1105 | C75: Plomberie | D75: Unité | F75: 20000 | G75: 35000 | H75: 0.75 | I75: 1 | J75: 30000 | L75: 0 | M75: 0 | N75: 1 | O75: 8 | P75: RÉAPPROVISIONNER | Q75: 20000
A76: FADCO | B76: ROBINET DOUCHE TWIST ROS4109 | C76: Plomberie | D76: Unité | F76: 7500 | G76: 12000 | H76: 0.6 | I76: 1 | J76: 10000 | L76: 0 | M76: 0 | N76: 1 | O76: 8 | P76: RÉAPPROVISIONNER | Q76: 7500
A77: FADCO | B77: ROBINET LAVABO TWIST ROS4101 | C77: Plomberie | D77: Unité | F77: 12000 | G77: 20000 | H77: 0.66666667 | I77: 1 | J77: 18000 | L77: 0 | M77: 0 | N77: 1 | O77: 8 | P77: RÉAPPROVISIONNER | Q77: 12000
A78: FADCO | B78: ROBINET CUISINE TWIST ROS4106 | C78: Plomberie | D78: Unité | F78: 13500 | G78: 20000 | H78: 0.48148148 | I78: 1 | J78: 18000 | L78: 0 | M78: 0 | N78: 1 | O78: 8 | P78: RÉAPPROVISIONNER | Q78: 13500
A79: FADCO | B79: ROBINET PUISAGE A BOISSEAU 16/20 | C79: Plomberie | D79: Unité | F79: 2800 | G79: 3500 | H79: 0.25 | J79: 3500 | L79: 0 | M79: 0 | N79: 0 | O79: 8 | P79: RÉAPPROVISIONNER | Q79: 0
A80: FADCO | B80: ROBINET PUISAGE A BOISSEAU 20/25 | C80: Plomberie | D80: Unité | F80: 3800 | G80: 5500 | H80: 0.44736842 | I80: 1 | J80: 4500 | L80: 0 | M80: 0 | N80: 1 | O80: 8 | P80: RÉAPPROVISIONNER | Q80: 3800
A81: FADCO | B81: ROBINET D'ARRET A BOISSEAU 16/20 | C81: Plomberie | D81: Unité | F81: 1800 | G81: 3500 | H81: 0.94444444 | I81: 1 | J81: 3000 | L81: 0 | M81: 0 | N81: 1 | O81: 8 | P81: RÉAPPROVISIONNER | Q81: 1800
A82: FADCO | B82: ROBINET D'ARRET A BOISSEAU 20/25 | C82: Plomberie | D82: Unité | F82: 3800 | G82: 6000 | H82: 0.57894737 | J82: 5000 | L82: 0 | M82: 0 | N82: 0 | O82: 8 | P82: RÉAPPROVISIONNER | Q82: 0
A83: FADCO | B83: MECANISME OLI | C83: Plomberie | D83: Unité | F83: 5500 | G83: 10000 | H83: 0.81818182 | J83: 8000 | L83: 0 | M83: 0 | N83: 0 | O83: 8 | P83: RÉAPPROVISIONNER | Q83: 0
A84: FADCO | B84: MECANISME POUSSOIRE FLOTEUR S/B | C84: Plomberie | D84: Unité | F84: 8000 | G84: 12000 | H84: 0.5 | J84: 12000 | L84: 0 | M84: 0 | N84: 0 | O84: 8 | P84: RÉAPPROVISIONNER | Q84: 0
A85: FADCO | B85: ROBINET EQUERRE DOUBLE SODA | C85: Plomberie | D85: Unité | F85: 11000 | G85: 20000 | H85: 0.81818182 | J85: 15000 | L85: 0 | M85: 0 | N85: 0 | O85: 8 | P85: RÉAPPROVISIONNER | Q85: 0
A86: FADCO | B86: SHUT OFF SOSA BLANC-101 ALW | C86: Outillage / Peinture | D86: Unité | F86: 5000 | G86: 10000 | H86: 1 | J86: 8000 | L86: 0 | M86: 0 | N86: 0 | O86: 8 | P86: RÉAPPROVISIONNER | Q86: 0
A87: SIKA | B87: SIKACERAM Mortier-Colles | C87: Gros œuvre | D87: Unité | F87: 3250 | G87: 5000 | H87: 0.53846154 | I87: 5 | J87: 4000 | L87: 0 | M87: 0 | N87: 5 | O87: 8 | P87: RÉAPPROVISIONNER | Q87: 16250
A88: IFAN | B88: TES PPR 20/25 | C88: Plomberie | D88: Unité | F88: 100 | G88: 500 | H88: 4 | I88: 20 | J88: 400 | L88: 0 | M88: 0 | N88: 20 | O88: 8 | P88: OK | Q88: 2000
A89: IFAN | B89: TES PPR 16/20 | C89: Plomberie | D89: Unité | F89: 75 | G89: 300 | H89: 3 | I89: 40 | J89: 200 | L89: 0 | M89: 0 | N89: 40 | O89: 200 | P89: RÉAPPROVISIONNER | Q89: 3000
A90: FORCE | B90: BOUCHON GALVA 20/25 FEMELLE | C90: Plomberie | D90: Unité | F90: 200 | G90: 500 | H90: 1.5 | L90: 0 | M90: 0 | N90: 0 | P90: RÉAPPROVISIONNER | Q90: 0
A91: FORCE | B91: BOUCHON GALVA 20/25 MAL | C91: Plomberie | D91: Unité | F91: 200 | G91: 500 | H91: 1.5 | L91: 0 | M91: 0 | N91: 0 | P91: RÉAPPROVISIONNER | Q91: 0
A92: FORCE | B92: BOUCHON GALVA 16/20 FEMELLE | C92: Plomberie | D92: Unité | F92: 150 | G92: 500 | H92: 2.3333333 | L92: 0 | M92: 0 | N92: 0 | P92: RÉAPPROVISIONNER | Q92: 0
A93: FORCE | B93: BOUCHON GALVA 16/20 MAL | C93: Plomberie | D93: Unité | F93: 100 | G93: 500 | H93: 4 | L93: 0 | M93: 0 | N93: 0 | P93: RÉAPPROVISIONNER | Q93: 0
A94: INDUSTRAP | B94: VERNIS CLAIR 1L | C94: Outillage / Peinture | D94: Unité | F94: 3600 | G94: 4000 | H94: 0.11111111 | J94: 4000 | L94: 0 | M94: 0 | N94: 0 | P94: RÉAPPROVISIONNER | Q94: 0
A95: INDUSTRAP | B95: VERNIS ROUGE 1L | C95: Outillage / Peinture | D95: Unité | F95: 3600 | G95: 4000 | H95: 0.11111111 | J95: 4000 | L95: 0 | M95: 0 | N95: 0 | P95: RÉAPPROVISIONNER | Q95: 0
A96: INDUSTRAP | B96: VERNIS ROUGE 4L | C96: Outillage / Peinture | D96: Unité | F96: 12500 | G96: 15000 | H96: 0.2 | L96: 0 | M96: 0 | N96: 0 | P96: RÉAPPROVISIONNER | Q96: 0
A97: INDUSTRAP | B97: VERNIS CLAIR 4L | C97: Outillage / Peinture | D97: Unité | F97: 12500 | G97: 15000 | H97: 0.2 | L97: 0 | M97: 0 | N97: 0 | P97: RÉAPPROVISIONNER | Q97: 0
A98: INDUSTRAP | B98: VERNIS A EAU 1L | C98: Outillage / Peinture | D98: Unité | F98: 2200 | G98: 3000 | H98: 0.36363636 | J98: 3000 | L98: 0 | M98: 0 | N98: 0 | P98: RÉAPPROVISIONNER | Q98: 0
A99: FORCE | B99: COLLIER EN FER+CAOUTCHOUC D100 | C99: Plomberie | D99: Unité | F99: 650 | G99: 1000 | H99: 0.53846154 | J99: 1000 | L99: 0 | M99: 0 | N99: 0 | P99: RÉAPPROVISIONNER | Q99: 0
A100: FORCE | B100: COLLIER EN FER+CAOUTCHOUC D110 | C100: Plomberie | D100: Unité | F100: 600 | G100: 1000 | H100: 0.66666667 | J100: 1000 | L100: 0 | M100: 0 | N100: 0 | P100: RÉAPPROVISIONNER | Q100: 0
A101: FORCE | B101: COLLIER EN FER+CAOUTCHOUC D125 | C101: Plomberie | D101: Unité | F101: 750 | G101: 1000 | H101: 0.33333333 | J101: 1000 | L101: 0 | M101: 0 | N101: 0 | P101: RÉAPPROVISIONNER | Q101: 0
A102: FORCE | B102: COLLIER EN FER+CAOUTCHOUC D32 | C102: Plomberie | D102: Unité | F102: 350 | G102: 800 | H102: 1.2857143 | J102: 600 | L102: 0 | M102: 0 | N102: 0 | P102: RÉAPPROVISIONNER | Q102: 0
A103: FORCE | B103: COLLIER EN FER+CAOUTCHOUC D40 | C103: Plomberie | D103: Unité | F103: 400 | G103: 1000 | H103: 1.5 | J103: 800 | L103: 0 | M103: 0 | N103: 0 | P103: RÉAPPROVISIONNER | Q103: 0
A104: FORCE | B104: COLLIER EN FER+CAOUTCHOUC D25 | C104: Plomberie | D104: Unité | F104: 300 | G104: 500 | H104: 0.66666667 | L104: 0 | M104: 0 | N104: 0 | P104: RÉAPPROVISIONNER | Q104: 0
A105: FORCE | B105: COLLIER EN FER+CAOUTCHOUC D10 | C105: Plomberie | D105: Unité | F105: 40 | G105: 200 | H105: 4 | L105: 0 | M105: 0 | N105: 0 | P105: RÉAPPROVISIONNER | Q105: 0
...

Sheet Mouvements
A2: JOURNAL DES MOUVEMENTS (ENTRÉES / SORTIES)
A3: Saisie quotidienne de toutes les ventes en caisse et des réapprovisionnements
A4: Date | B4: Type Mouvement | C4: Code Article | D4: Catégorie | E4: Quantité | F4: Prix Unitaire (FCFA) | G4: Total FCFA | H4: Client / Fournisseur
A5: 2026-08-20 | B5: Entrée | C5: ART-001 | E5: 50 | F5: 4200 | G5: 210000 | H5: SOCIMAT Fournisseur
A6: 2026-08-20 | B6: Entrée | C6: ART-002 | E6: 100 | F6: 3100 | G6: 310000 | H6: SOTACI Ferraille
A7: 2026-08-21 | B7: Sortie | C7: ART-001 | E7: 10 | F7: 4800 | G7: 48000 | H7: Entreprise BTP PHOENIX
A8: 2026-08-21 | B8: Sortie | C8: ART-002 | E8: 15 | F8: 3700 | G8: 55500 | H8: Client Comptoir - M. Traoré
A9: 2026-08-21 | B9: Sortie | C9: ART-003 | E9: 5 | F9: 3200 | G9: 16000 | H9: Plombier Kouassi
A10: 2026-08-22 | B10: Sortie | C10: ART-005 | E10: 4 | F10: 17500 | G10: 70000 | H10: Electricien Koffi
A11: 2026-08-22 | B11: Entrée | C11: ART-004 | E11: 10 | F11: 18500 | G11: 185000 | H11: Peintures SIPEC
A12: 2026-08-22 | B12: Sortie | C12: ART-004 | E12: 2 | F12: 23500 | G12: 47000 | H12: Client Particulier
A13: 2026-08-22 | B13: Sortie | C13: ART-006 | E13: 500 | F13: 320 | G13: 160000 | H13: Chantier Résidence Angré
A14: 2026-08-22 | B14: Sortie | C14: ART-001 | E14: 45 | F14: 4800 | G14: 216000 | H14: Client BTP - Extension Villa
D15: TOTAL DES FLUX | E15: 741 | G15: 1317500
A16: 2026-09-28 | B16: Sortie | C16: ART-PIN | D16: PINCEAU N°70 | E16: 1 | F16: 500 | G16: 500 | H16: Client Comptoir
A17: 2026-09-28 | B17: Sortie | C17: ART-PIN | D17: PINCEAU N°50 | E17: 1 | F17: 500 | G17: 500 | H17: Client Comptoir
A18: 2026-09-28 | B18: Sortie | C18: ART-CHE | D18: CHEVILLE + VIS N°12 25PCS/BTE | E18: 1 | F18: 1000 | G18: 1000 | H18: Client Comptoir
A19: 46293 | B19: Sortie | C19: ART | D19: equerre | E19: 1 | F19: 1000 | G19: 1000 | H19: Client Comptoir
A20: 46293 | B20: Sortie | C20: ART | D20: platre | E20: 1 | F20: 500 | G20: 500 | H20: Client Comptoir
A21: 46293 | B21: Sortie | C21: ART | D21: Tourne vis | E21: 1 | F21: 1000 | G21: 1000 | H21: Client Comptoir
A22: 46293 | B22: Sortie | C22: ART | D22: Petit pinceau(dessin) | E22: 2 | F22: 300 | G22: 300 | H22: Client Comptoir
